vectortoapple/__init__.py
vectortoapple/convert.py
vectortoapple-0.1.3.dist-info/LICENSE
vectortoapple-0.1.3.dist-info/METADATA
vectortoapple-0.1.3.dist-info/WHEEL
vectortoapple-0.1.3.dist-info/entry_points.txt
vectortoapple-0.1.3.dist-info/top_level.txt
vectortoapple-0.1.3.dist-info/RECORD
