Metadata-Version: 2.1
Name: vectortoapple
Version: 0.1.3
Summary: Convert Android vector drawable XML files to Apple's Asset Catalog format
Home-page: https://github.com/Ginder-Singh/vectortoapple
Author: Ginder Singh
Author-email: ginderksingh@gmail.com
Classifier: Programming Language :: Python :: 3
Classifier: License :: OSI Approved :: MIT License
Classifier: Operating System :: OS Independent
Requires-Python: >=3.6
License-File: LICENSE
Requires-Dist: cairosvg
Requires-Dist: Pillow
Requires-Dist: tqdm
